<?xml version="1.0" encoding="utf-8"?>
<root>
  <ScenarioPylon>
    <X>976.4272</X>
    <Y>0.2794306</Y>
    <Z>1362.823</Z>
    <RX>270</RX>
    <RY>0</RY>
    <RZ>0</RZ>
  </ScenarioPylon>
  <ScenarioPylon>
    <X>976.2095</X>
    <Y>0.2794306</Y>
    <Z>1358.912</Z>
    <RX>270</RX>
    <RY>0</RY>
    <RZ>0</RZ>
  </ScenarioPylon>
  <ScenarioPylon>
    <X>979.3062</X>
    <Y>0.2794306</Y>
    <Z>1361.749</Z>
    <RX>270</RX>
    <RY>0</RY>
    <RZ>0</RZ>
  </ScenarioPylon>
  <ScenarioPylon>
    <X>979.0702</X>
    <Y>0.2794306</Y>
    <Z>1357.769</Z>
    <RX>270</RX>
    <RY>0</RY>
    <RZ>0</RZ>
  </ScenarioPylon>
  <ScenarioPylon>
    <X>982.7802</X>
    <Y>0.2794307</Y>
    <Z>1360.636</Z>
    <RX>270</RX>
    <RY>0</RY>
    <RZ>0</RZ>
  </ScenarioPylon>
  <ScenarioPylon>
    <X>981.7672</X>
    <Y>0.2794306</Y>
    <Z>1356.676</Z>
    <RX>270</RX>
    <RY>0</RY>
    <RZ>0</RZ>
  </ScenarioPylon>
  <ScenarioPylon>
    <X>986.1784</X>
    <Y>0.2794306</Y>
    <Z>1357.423</Z>
    <RX>270</RX>
    <RY>0</RY>
    <RZ>0</RZ>
  </ScenarioPylon>
  <ScenarioPylon>
    <X>995.2047</X>
    <Y>0.2794306</Y>
    <Z>1353.158</Z>
    <RX>270</RX>
    <RY>0</RY>
    <RZ>0</RZ>
  </ScenarioPylon>
  <ScenarioPylon>
    <X>1003.152</X>
    <Y>0.2794307</Y>
    <Z>1347.766</Z>
    <RX>270</RX>
    <RY>0</RY>
    <RZ>0</RZ>
  </ScenarioPylon>
  <ScenarioPylon>
    <X>1006.462</X>
    <Y>0.2794306</Y>
    <Z>1340.331</Z>
    <RX>270</RX>
    <RY>0</RY>
    <RZ>0</RZ>
  </ScenarioPylon>
  <ScenarioPylon>
    <X>1006.513</X>
    <Y>0.2794306</Y>
    <Z>1331.867</Z>
    <RX>270</RX>
    <RY>0</RY>
    <RZ>0</RZ>
  </ScenarioPylon>
  <ScenarioPylon>
    <X>1006.321</X>
    <Y>0.2794307</Y>
    <Z>1324.684</Z>
    <RX>270</RX>
    <RY>0</RY>
    <RZ>0</RZ>
  </ScenarioPylon>
</root>